lvmthin_helper/__init__.py
lvmthin_helper/main.py
lvmthin_helper/prompts.py
lvmthin_helper-2025.12.21233703.dist-info/METADATA
lvmthin_helper-2025.12.21233703.dist-info/WHEEL
lvmthin_helper-2025.12.21233703.dist-info/top_level.txt
lvmthin_helper-2025.12.21233703.dist-info/RECORD
