Metadata-Version: 2.4
Name: lvmthin-helper
Version: 2025.12.21233703
Summary: lvmthin-helper automates LVM Thin Provisioning management by analyzing user inputs and current setups, offering optimized configurations and troubleshooting steps for efficient storage.
Author-email: lvmthin-helper <hi@eugene.plus>
License: MIT
Project-URL: Homepage, https://github.com/chigwell/lvmthin-helper
Requires-Python: >=3.9
Requires-Dist: langchain-llm7>=0.0.0
Requires-Dist: llmatch-messages>=0.0.0
Requires-Dist: langchain-core>=0.3.0
